<?xml version="1.0" encoding="ISO-8859-1"?><rankingM40>	<equipo id="" puntos="457" nombreCorto="RBB">Real Betisman Balompié</equipo>	<equipo id="" puntos="459,5" nombreCorto="RSC">Real Servelete de Carfesan</equipo>	<equipo id="" puntos="393,5" nombreCorto="ThP">ThePiso</equipo>	<equipo id="" puntos="358" nombreCorto="Pit">Pitisianos SAD</equipo>	<equipo id="" puntos="219,5" nombreCorto="CON">CONGRIO F.C.</equipo>	<equipo id="" puntos="148,5" nombreCorto="Esp">Espino F.C</equipo>	<equipo id="" puntos="293,5" nombreCorto="Hap">Hapiio</equipo>	<equipo id="" puntos="146" nombreCorto="Cnz">Caranza F.C.</equipo>	<equipo id="" puntos="167" nombreCorto="oll">ollauris F.C.</equipo>	<equipo id="" puntos="290,5" nombreCorto="Jum">Jumfrys F.K.</equipo>	<equipo id="" puntos="117,5" nombreCorto="ADP">A.D. Dimitri Piterman</equipo>	<equipo id="" puntos="242,5" nombreCorto="Inf">Inframundo CD Drogadictos Anónimos</equipo>	<equipo id="" puntos="143" nombreCorto="Buk">Bukakke Team</equipo>	<equipo id="" puntos="10" nombreCorto="reg">reguerones</equipo>	<equipo id="" puntos="103" nombreCorto="mil">milan chupao</equipo>	<equipo id="" puntos="57" nombreCorto="RGC">Raul Gran Capitan</equipo>	<equipo id="" puntos="6" nombreCorto="par">partyman's</equipo>	<equipo id="" puntos="18" nombreCorto="cha">chaconcines</equipo>	<equipo id="" puntos="101" nombreCorto="Cor">Cordoba SAD</equipo>	<equipo id="" puntos="19" nombreCorto="ptx">patxy's TEAM</equipo>	<equipo id="" puntos="11" nombreCorto="Ros">Roscuro Team</equipo>	<equipo id="" puntos="0" nombreCorto="yog">El yogur mecanico</equipo>	<equipo id="" puntos="76,5" nombreCorto="Dog">Dogt</equipo></rankingM40>
